[
        {
            "command": "unbound",
            "keys": "ctrl+comma"
        },
        {
            "command": "unbound",
            "keys": "ctrl+shift+w"
        },
        {
            "command": "unbound",
            "keys": "ctrl+d"
        },
        {
            "command": "unbound",
            "keys": "ctrl+f"
        },
        {
            "command": "unbound",
            "keys": "ctrl+space"
        },
        {
            "command": "unbound",
            "keys": "ctrl+shift+f"
        },
        {
            "command": "unbound",
            "keys": "ctrl+shift+n"
        },
        {
            "command": "unbound",
            "keys": "ctrl+alt+down"
        },
        {
            "command": "unbound",
            "keys": "ctrl+alt+left"
        },
        {
            "command": "unbound",
            "keys": "ctrl+alt+up"
        },
        {
            "command": "unbound",
            "keys": "ctrl+alt+right"
        },
        {
            "command": "unbound",
            "keys": "alt+down"
        },
        {
            "command": "unbound",
            "keys": "alt+left"
        },
        {
            "command": "unbound",
            "keys": "alt+up"
        },
        {
            "command": "unbound",
            "keys": "alt+right"
        },
        {
            "command": "unbound",
            "keys": "alt+shift+right"
        },
        {
            "command": "unbound",
            "keys": "alt+shift+down"
        },
        {
            "command": "unbound",
            "keys": "alt+shift+left"
        },
        {
            "command": "unbound",
            "keys": "alt+shift+up"
        },
        {
            "command": "duplicateTab",
            "keys": "ctrl+shift+d"
        },
        {
            "command": 
            {
                "action": "closeTab"
            },
            "keys": "ctrl+f4"
        }
]
